tap_rev_io/__init__.py
tap_rev_io/client.py
tap_rev_io/schemas/Addresses.json
tap_rev_io/schemas/Agents.json
tap_rev_io/schemas/Announcements.json
tap_rev_io/schemas/Audits.json
tap_rev_io/schemas/BillProfiles.json
tap_rev_io/schemas/Bills.json
tap_rev_io/schemas/Charges.json
tap_rev_io/schemas/Contacts.json
tap_rev_io/schemas/ContactTypes.json
tap_rev_io/schemas/Credits.json
tap_rev_io/schemas/CustomerRelationships.json
tap_rev_io/schemas/Customers.json
tap_rev_io/schemas/Files.json
tap_rev_io/schemas/InventoryItem.json
tap_rev_io/schemas/InventoryTypes.json
tap_rev_io/schemas/Notes.json
tap_rev_io/schemas/NoteTypes.json
tap_rev_io/schemas/Orders.json
tap_rev_io/schemas/OrderServiceProducts.json
tap_rev_io/schemas/OrderServices.json
tap_rev_io/schemas/PackageProducts.json
tap_rev_io/schemas/Packages.json
tap_rev_io/schemas/PaymentAccounts.json
tap_rev_io/schemas/PaymentMethods.json
tap_rev_io/schemas/Payments.json
tap_rev_io/schemas/Processes.json
tap_rev_io/schemas/ProcessPhases.json
tap_rev_io/schemas/ProcessTasks.json
tap_rev_io/schemas/ProductGroups.json
tap_rev_io/schemas/Products.json
tap_rev_io/schemas/ProductTypes.json
tap_rev_io/schemas/ProviderAccounts.json
tap_rev_io/schemas/Providers.json
tap_rev_io/schemas/ReportCategories.json
tap_rev_io/schemas/Reports.json
tap_rev_io/schemas/RequestAddresses.json
tap_rev_io/schemas/RequestContacts.json
tap_rev_io/schemas/RequestProducts.json
tap_rev_io/schemas/Requests.json
tap_rev_io/schemas/RequestServices.json
tap_rev_io/schemas/RequestStatuses.json
tap_rev_io/schemas/RequestTemplates.json
tap_rev_io/schemas/ServiceInventory.json
tap_rev_io/schemas/ServiceProduct.json
tap_rev_io/schemas/Services.json
tap_rev_io/schemas/ServiceTypes.json
tap_rev_io/schemas/Tasks.json
tap_rev_io/schemas/TaskSteps.json
tap_rev_io/schemas/TaskTypes.json
tap_rev_io/schemas/TicketJournals.json
tap_rev_io/schemas/TicketProcesses.json
tap_rev_io/schemas/Tickets.json
tap_rev_io/schemas/UsagePlanGroups.json
tap_rev_io-0.0.4.dist-info/entry_points.txt
tap_rev_io-0.0.4.dist-info/WHEEL
tap_rev_io-0.0.4.dist-info/METADATA
tap_rev_io-0.0.4.dist-info/RECORD
