Metadata-Version: 2.1
Name: tap-rev-io
Version: 0.0.4
Summary: `tap-rev_io` is a Singer tap for rev_io, built with the Meltano SDK for Singer Taps.
License: Apache 2.0
Keywords: ELT,rev_io
Author: BI4ALL
Requires-Python: >=3.7.1,<3.11
Classifier: License :: Other/Proprietary License
Classifier: Programming Language :: Python :: 3
Classifier: Programming Language :: Python :: 3.10
Classifier: Programming Language :: Python :: 3.8
Classifier: Programming Language :: Python :: 3.9
Requires-Dist: requests (>=2.25.1,<3.0.0)
Requires-Dist: singer-sdk (>=0.4.7,<0.5.0)
